aspy_dependency_injection/__init__.py
aspy_dependency_injection/_aspy_undefined.py
aspy_dependency_injection/_async_concurrent_dictionary.py
aspy_dependency_injection/_integrations/__init__.py
aspy_dependency_injection/_integrations/_fastapi_dependency_injection.py
aspy_dependency_injection/_service_lookup/__init__.py
aspy_dependency_injection/_service_lookup/_async_factory_call_site.py
aspy_dependency_injection/_service_lookup/_call_site_chain.py
aspy_dependency_injection/_service_lookup/_call_site_factory.py
aspy_dependency_injection/_service_lookup/_call_site_kind.py
aspy_dependency_injection/_service_lookup/_call_site_runtime_resolver.py
aspy_dependency_injection/_service_lookup/_call_site_visitor.py
aspy_dependency_injection/_service_lookup/_constructor_call_site.py
aspy_dependency_injection/_service_lookup/_constructor_information.py
aspy_dependency_injection/_service_lookup/_parameter_information.py
aspy_dependency_injection/_service_lookup/_result_cache.py
aspy_dependency_injection/_service_lookup/_runtime_service_provider_engine.py
aspy_dependency_injection/_service_lookup/_service_call_site.py
aspy_dependency_injection/_service_lookup/_service_identifier.py
aspy_dependency_injection/_service_lookup/_service_provider_call_site.py
aspy_dependency_injection/_service_lookup/_service_provider_engine.py
aspy_dependency_injection/_service_lookup/_supports_async_context_manager.py
aspy_dependency_injection/_service_lookup/_supports_context_manager.py
aspy_dependency_injection/_service_lookup/_sync_factory_call_site.py
aspy_dependency_injection/_service_lookup/_typed_type.py
aspy_dependency_injection/_service_lookup/call_site_result_cache_location.py
aspy_dependency_injection/_service_lookup/service_cache_key.py
aspy_dependency_injection/abstractions/__init__.py
aspy_dependency_injection/abstractions/base_service_provider.py
aspy_dependency_injection/abstractions/service_scope.py
aspy_dependency_injection/abstractions/service_scope_factory.py
aspy_dependency_injection-0.2.0.dist-info/licenses/LICENSE
aspy_dependency_injection-0.2.0.dist-info/WHEEL
aspy_dependency_injection-0.2.0.dist-info/METADATA
aspy_dependency_injection-0.2.0.dist-info/RECORD
