Metadata-Version: 2.4
Name: aspy-dependency-injection
Version: 0.2.0
Summary: Dependency injection
Author: Andreu Codina
Author-email: Andreu Codina <30506301+AndreuCodina@users.noreply.github.com>
License-Expression: MIT
License-File: LICENSE
Classifier: Development Status :: 5 - Production/Stable
Classifier: Programming Language :: Python :: 3.14
Classifier: Intended Audience :: Developers
Requires-Dist: fastapi[standard-no-fastapi-cloud-cli]>=0.118.0
Requires-Python: >=3.14
Project-URL: Changelog, https://github.com/AndreuCodina/aspy-dependency-injection/releases
Project-URL: Documentation, https://github.com/AndreuCodina/aspy-dependency-injection
Project-URL: Homepage, https://github.com/AndreuCodina/aspy-dependency-injection
Project-URL: Repository, https://github.com/AndreuCodina/aspy-dependency-injection
